{
  "notes": [
    {
      "title": "Test Title",
      "text": "Test text",
      "id": "0"
    },
    {
      "title": "get coffee",
      "text": "go to starbucks",
      "id": "1"
    },
    {
      "title": "workout",
      "text": "workout ",
      "id": "2"
    },
    {
      "title": "go to the grocery store",
      "text": "get bread",
      "id": "3"
    },
    {
      "title": "run",
      "text": "run",
      "id": "4"
    },
    {
      "title": "jog",
      "text": "jog",
      "id": "5"
    },
    {
      "title": "do coding homework",
      "text": "challenge 11",
      "id": "6"
    },
    {
      "title": "Schoolwork",
      "text": "finish challenge 11",
      "id": "7"
    },
    {
      "title": "brush teeth",
      "text": "teeth",
      "id": "41f5f3e3-3d20-4d7e-8990-f8a442fd15b3"
    }
  ]
}